combot_installer/__init__.py
combot_installer/__main__.py
combot_installer/installer.py
shelle-0.1.2.dist-info/METADATA
shelle-0.1.2.dist-info/WHEEL
shelle-0.1.2.dist-info/entry_points.txt
shelle-0.1.2.dist-info/top_level.txt
shelle-0.1.2.dist-info/RECORD
