Metadata-Version: 2.1
Name: shelle
Version: 0.1.2
Summary: Terminal Assisstant
Author: Hkcode
Author-email: sissokoadel057@gmail.com
Classifier: Programming Language :: Python :: 3
Classifier: Programming Language :: Python :: 3.12
Classifier: License :: OSI Approved :: MIT License
